[
    {
        "原文": "周围的同学们无不惊呼：“哇！好漂亮的车！”",
        "场景": {
            "位置类型": "户外",
            "环境特点": [
                "白天",
                "阳光明媚"
            ],
            "场景特征": [
                "校园门口",
                "学生",
                "生活日用品",
                "豪车"
            ]
        },
        "幕": 38,
        "角色": [
            {
                "名字": "同学",
                "年龄": "青年",
                "动作": [
                    "惊呼"
                ],
                "视线与方向": "注视豪车",
                "表情": [
                    "惊讶",
                    "羡慕"
                ],
                "服装": {
                    "上衣": {
                        "物品": "T恤",
                        "款式": "简约",
                        "状态": "穿戴整洁"
                    },
                    "外套": {
                        "物品": "无",
                        "款式": "无",
                        "类型": "无",
                        "状态": "无",
                        "袖子": "无"
                    },
                    "配饰": {
                        "物品": "无",
                        "类型": "无"
                    }
                },
                "临时特征": [],
                "构图": "角色位于画面中央，镜头略微俯视"
            }
        ]
    },
    {
        "原文": "“玛德！布加迪威龙！两千多万的豪车啊！我们学校这是来了神豪少爷啊！”",
        "场景": {
            "位置类型": "户外",
            "环境特点": [
                "白天",
                "阳光明媚"
            ],
            "场景特征": [
                "校园门口",
                "学生",
                "生活日用品",
                "豪车"
            ]
        },
        "幕": 38,
        "角色": [
            {
                "名字": "同学",
                "年龄": "青年",
                "动作": [
                    "惊呼"
                ],
                "视线与方向": "注视豪车",
                "表情": [
                    "惊讶",
                    "羡慕"
                ],
                "服装": {
                    "上衣": {
                        "物品": "T恤",
                        "款式": "简约",
                        "状态": "穿戴整洁"
                    },
                    "外套": {
                        "物品": "无",
                        "款式": "无",
                        "类型": "无",
                        "状态": "无",
                        "袖子": "无"
                    },
                    "配饰": {
                        "物品": "无",
                        "类型": "无"
                    }
                },
                "临时特征": [],
                "构图": "角色位于画面中央，镜头略微俯视"
            }
        ]
    },
    {
        "原文": "当所有人的目光都集中在那辆车上的时候，我的目光也不禁被吸引了过去。",
        "场景": {
            "位置类型": "户外",
            "环境特点": [
                "白天",
                "阳光明媚"
            ],
            "场景特征": [
                "校园门口",
                "学生",
                "生活日用品",
                "豪车"
            ]
        },
        "幕": 38,
        "角色": [
            {
                "名字": "我",
                "年龄": "青年",
                "动作": [
                    "注视豪车"
                ],
                "视线与方向": "注视豪车",
                "表情": [
                    "好奇",
                    "惊讶"
                ],
                "服装": {
                    "上衣": {
                        "物品": "白衬衫",
                        "款式": "纽扣式",
                        "状态": "穿戴整洁"
                    },
                    "外套": {
                        "物品": "蓝色夹克",
                        "款式": "敞开的夹克",
                        "类型": "带帽夹克",
                        "状态": "帽子放下",
                        "袖子": "长袖"
                    },
                    "配饰": {
                        "物品": "黑色项圈",
                        "类型": "简约款"
                    }
                },
                "临时特征": [
                    "黑眼圈",
                    "手持钥匙"
                ],
                "构图": "主角位于画面中央，镜头略微俯视"
            }
        ]
    },
    {
        "原文": "“儿子，上车！”我在车旁喊了一声，看到杨自奎兴奋地跑了过去，拉开了车门，竟然一屁股坐了进去。",
        "场景": {
            "位置类型": "户外",
            "环境特点": [
                "白天",
                "阳光明媚"
            ],
            "场景特征": [
                "校园门口",
                "学生",
                "生活日用品",
                "豪车"
            ]
        },
        "幕": 38,
        "角色": [
            {
                "名字": "杨自奎",
                "年龄": "青年",
                "动作": [
                    "跑向豪车",
                    "拉开车门",
                    "坐进车内"
                ],
                "视线与方向": "注视豪车",
                "表情": [
                    "兴奋",
                    "激动"
                ],
                "服装": {
                    "上衣": {
                        "物品": "T恤",
                        "款式": "简约",
                        "状态": "穿戴整洁"
                    },
                    "外套": {
                        "物品": "无",
                        "款式": "无",
                        "类型": "无",
                        "状态": "无",
                        "袖子": "无"
                    },
                    "配饰": {
                        "物品": "无",
                        "类型": "无"
                    }
                },
                "临时特征": [],
                "构图": "角色位于画面中央，镜头略微俯视"
            }
        ]
    },
    {
        "原文": "周围的同学们立刻炸开了锅：“哇！是杨胖子！他，他爸爸是富豪吗？”",
        "场景": {
            "位置类型": "户外",
            "环境特点": [
                "白天",
                "阳光明媚"
            ],
            "场景特征": [
                "校园门口",
                "学生",
                "生活日用品",
                "豪车"
            ]
        },
        "幕": 38,
        "角色": [
            {
                "名字": "同学",
                "年龄": "青年",
                "动作": [
                    "惊呼"
                ],
                "视线与方向": "注视杨自奎",
                "表情": [
                    "惊讶",
                    "好奇"
                ],
                "服装": {
                    "上衣": {
                        "物品": "T恤",
                        "款式": "简约",
                        "状态": "穿戴整洁"
                    },
                    "外套": {
                        "物品": "无",
                        "款式": "无",
                        "类型": "无",
                        "状态": "无",
                        "袖子": "无"
                    },
                    "配饰": {
                        "物品": "无",
                        "类型": "无"
                    }
                },
                "临时特征": [],
                "构图": "角色位于画面中央，镜头略微俯视"
            }
        ]
    },
    {
        "原文": "“杨胖子是豪门二代！我刚才听到那人叫他儿子！”",
        "场景": {
            "位置类型": "户外",
            "环境特点": [
                "白天",
                "阳光明媚"
            ],
            "场景特征": [
                "校园门口",
                "学生",
                "生活日用品",
                "豪车"
            ]
        },
        "幕": 38,
        "角色": [
            {
                "名字": "同学",
                "年龄": "青年",
                "动作": [
                    "惊呼"
                ],
                "视线与方向": "注视杨自奎",
                "表情": [
                    "惊讶",
                    "羡慕"
                ],
                "服装": {
                    "上衣": {
                        "物品": "T恤",
                        "款式": "简约",
                        "状态": "穿戴整洁"
                    },
                    "外套": {
                        "物品": "无",
                        "款式": "无",
                        "类型": "无",
                        "状态": "无",
                        "袖子": "无"
                    },
                    "配饰": {
                        "物品": "无",
                        "类型": "无"
                    }
                },
                "临时特征": [],
                "构图": "角色位于画面中央，镜头略微俯视"
            }
        ]
    }
]