[
    {
        "原文": "达万广场可是明星企业，多少人争相合作，我的砍价简直是狠得不留情面。",
        "场景": {
            "位置类型": "室内",
            "环境特点": [
                "明亮",
                "白天"
            ],
            "场景特征": [
                "达万广场",
                "市场管理部",
                "高档接待室"
            ]
        },
        "幕": 18,
        "角色": [
            {
                "名字": "我",
                "年龄": "青年",
                "动作": [
                    "坐在沙发上，双手交叉"
                ],
                "视线与方向": "注视观众",
                "表情": [
                    "自信",
                    "坚定"
                ],
                "服装": {
                    "上衣": {
                        "物品": "白衬衫",
                        "款式": "纽扣式",
                        "状态": "穿戴整洁"
                    },
                    "外套": {
                        "物品": "蓝色夹克",
                        "款式": "敞开的夹克",
                        "类型": "带帽夹克",
                        "状态": "帽子放下",
                        "袖子": "长袖"
                    },
                    "配饰": {
                        "物品": "黑色项圈",
                        "类型": "简约款"
                    }
                },
                "临时特征": [
                    "黑眼圈"
                ],
                "构图": "主角位于画面中央，镜头略微俯视"
            }
        ]
    },
    {
        "原文": "马士博的嘴角微微抽搐，显然不想轻易让步：“史总，这生意不是这样谈的，您这样没法……”",
        "场景": {
            "位置类型": "室内",
            "环境特点": [
                "明亮",
                "白天"
            ],
            "场景特征": [
                "达万广场",
                "市场管理部",
                "高档接待室"
            ]
        },
        "幕": 18,
        "角色": [
            {
                "名字": "马士博",
                "年龄": "中年",
                "动作": [
                    "坐在对面沙发上，嘴角微微抽搐"
                ],
                "视线与方向": "注视观众",
                "表情": [
                    "紧张",
                    "犹豫"
                ],
                "服装": {
                    "上衣": {
                        "物品": "西装衬衫",
                        "款式": "纽扣式",
                        "状态": "穿戴整洁"
                    },
                    "外套": {
                        "物品": "深色西装",
                        "款式": "合身",
                        "类型": "西装外套",
                        "状态": "穿戴整齐",
                        "袖子": "长袖"
                    },
                    "配饰": {
                        "物品": "领带",
                        "类型": "条纹款"
                    }
                },
                "临时特征": [],
                "构图": "角色位于画面左侧，镜头略微俯视"
            }
        ]
    },
    {
        "原文": "我不打算让他继续说下去，直接打断：“最高给到七成，能成就成，不能我凭着金鳞、万荣也够了！大不了多安排点人过去。如果谈不了，那就不必谈了！”",
        "场景": {
            "位置类型": "室内",
            "环境特点": [
                "明亮",
                "白天"
            ],
            "场景特征": [
                "达万广场",
                "市场管理部",
                "高档接待室"
            ]
        },
        "幕": 18,
        "角色": [
            {
                "名字": "我",
                "年龄": "青年",
                "动作": [
                    "双手摊开，语气坚定"
                ],
                "视线与方向": "注视观众",
                "表情": [
                    "决断",
                    "不容置疑"
                ],
                "服装": {
                    "上衣": {
                        "物品": "白衬衫",
                        "款式": "纽扣式",
                        "状态": "穿戴整洁"
                    },
                    "外套": {
                        "物品": "蓝色夹克",
                        "款式": "敞开的夹克",
                        "类型": "带帽夹克",
                        "状态": "帽子放下",
                        "袖子": "长袖"
                    },
                    "配饰": {
                        "物品": "黑色项圈",
                        "类型": "简约款"
                    }
                },
                "临时特征": [
                    "黑眼圈"
                ],
                "构图": "主角位于画面中央，镜头略微俯视"
            }
        ]
    },
    {
        "原文": "说着，我起身准备离开。",
        "场景": {
            "位置类型": "室内",
            "环境特点": [
                "明亮",
                "白天"
            ],
            "场景特征": [
                "达万广场",
                "市场管理部",
                "高档接待室"
            ]
        },
        "幕": 18,
        "角色": [
            {
                "名字": "我",
                "年龄": "青年",
                "动作": [
                    "起身，准备离开"
                ],
                "视线与方向": "注视观众",
                "表情": [
                    "决断",
                    "坚定"
                ],
                "服装": {
                    "上衣": {
                        "物品": "白衬衫",
                        "款式": "纽扣式",
                        "状态": "穿戴整洁"
                    },
                    "外套": {
                        "物品": "蓝色夹克",
                        "款式": "敞开的夹克",
                        "类型": "带帽夹克",
                        "状态": "帽子放下",
                        "袖子": "长袖"
                    },
                    "配饰": {
                        "物品": "黑色项圈",
                        "类型": "简约款"
                    }
                },
                "临时特征": [
                    "黑眼圈"
                ],
                "构图": "主角位于画面中央，镜头略微俯视"
            }
        ]
    },
    {
        "原文": "马士博显然感受到了压力，急忙道：“别急嘛！容我向总部申请一下，毕竟这加起来，可是一笔不小的费用。”",
        "场景": {
            "位置类型": "室内",
            "环境特点": [
                "明亮",
                "白天"
            ],
            "场景特征": [
                "达万广场",
                "市场管理部",
                "高档接待室"
            ]
        },
        "幕": 18,
        "角色": [
            {
                "名字": "马士博",
                "年龄": "中年",
                "动作": [
                    "急忙伸手，试图阻止"
                ],
                "视线与方向": "注视观众",
                "表情": [
                    "紧张",
                    "急切"
                ],
                "服装": {
                    "上衣": {
                        "物品": "西装衬衫",
                        "款式": "纽扣式",
                        "状态": "穿戴整洁"
                    },
                    "外套": {
                        "物品": "深色西装",
                        "款式": "合身",
                        "类型": "西装外套",
                        "状态": "穿戴整齐",
                        "袖子": "长袖"
                    },
                    "配饰": {
                        "物品": "领带",
                        "类型": "条纹款"
                    }
                },
                "临时特征": [],
                "构图": "角色位于画面左侧，镜头略微俯视"
            }
        ]
    },
    {
        "原文": "他并不是在乎租金，而是怕我搞的促销活动影响了他们的竞争力。",
        "场景": {
            "位置类型": "室内",
            "环境特点": [
                "明亮",
                "白天"
            ],
            "场景特征": [
                "达万广场",
                "市场管理部",
                "高档接待室"
            ]
        },
        "幕": 18,
        "角色": [
            {
                "名字": "马士博",
                "年龄": "中年",
                "动作": [
                    "低头沉思"
                ],
                "视线与方向": "注视观众",
                "表情": [
                    "担忧",
                    "沉思"
                ],
                "服装": {
                    "上衣": {
                        "物品": "西装衬衫",
                        "款式": "纽扣式",
                        "状态": "穿戴整洁"
                    },
                    "外套": {
                        "物品": "深色西装",
                        "款式": "合身",
                        "类型": "西装外套",
                        "状态": "穿戴整齐",
                        "袖子": "长袖"
                    },
                    "配饰": {
                        "物品": "领带",
                        "类型": "条纹款"
                    }
                },
                "临时特征": [],
                "构图": "角色位于画面左侧，镜头略微俯视"
            }
        ]
    }
]