[
    {
        "text": "The March Hare took the watch and looked at it gloomily.",
        "scene": {
            "location_type": "indoor",
            "environment_features": [
                "dim lighting",
                "evening",
                "tea party setting"
            ],
            "scene_features": [
                "tea table",
                "tea cups",
                "pastries"
            ]
        },
        "act": 0,
        "characters": [
            {
                "name": "March Hare",
                "age": "adult",
                "actions": [
                    "holding a pocket watch",
                    "looking at the watch"
                ],
                "gaze_and_direction": "looking at the viewer",
                "expression": [
                    "gloomy",
                    "pensive"
                ],
                "costume": {
                    "top": {
                        "item": "waistcoat",
                        "style": "vintage",
                        "condition": "slightly worn"
                    },
                    "accessories": {
                        "item": "pocket watch",
                        "type": "antique"
                    }
                },
                "temporary_features": [],
                "composition": "March Hare centered, camera slightly overhead"
            }
        ]
    },
    {
        "text": "Alice had been looking over his shoulder with some curiosity.",
        "scene": {
            "location_type": "indoor",
            "environment_features": [
                "dim lighting",
                "evening",
                "tea party setting"
            ],
            "scene_features": [
                "tea table",
                "tea cups",
                "pastries"
            ]
        },
        "act": 0,
        "characters": [
            {
                "name": "Alice",
                "age": "young adult",
                "actions": [
                    "leaning slightly",
                    "looking over March Hare's shoulder"
                ],
                "gaze_and_direction": "looking at the watch",
                "expression": [
                    "curious",
                    "interested"
                ],
                "costume": {
                    "top": {
                        "item": "blue dress",
                        "style": "Victorian",
                        "condition": "neatly worn"
                    },
                    "accessories": {
                        "item": "white apron",
                        "type": "plain"
                    }
                },
                "temporary_features": [],
                "composition": "Alice positioned slightly to the right, camera at eye level"
            }
        ]
    },
    {
        "text": "What a funny watch!",
        "scene": {
            "location_type": "indoor",
            "environment_features": [
                "dim lighting",
                "evening",
                "tea party setting"
            ],
            "scene_features": [
                "tea table",
                "tea cups",
                "pastries"
            ]
        },
        "act": 0,
        "characters": [
            {
                "name": "I",
                "age": "young adult",
                "actions": [
                    "pointing at the watch"
                ],
                "gaze_and_direction": "looking at the viewer",
                "expression": [
                    "amused",
                    "smiling"
                ],
                "costume": {
                    "top": {
                        "item": "white shirt",
                        "style": "button-up",
                        "condition": "neatly worn"
                    },
                    "jacket": {
                        "item": "blue jacket",
                        "style": "open jacket",
                        "type": "hooded jacket",
                        "condition": "hood down",
                        "sleeves": "long"
                    },
                    "accessories": {
                        "item": "black choker",
                        "type": "minimalistic"
                    }
                },
                "temporary_features": [
                    "dark circles under the eyes"
                ],
                "composition": "Main character centered, camera slightly overhead"
            }
        ]
    }
]